PyImageML/__init__.py
PyImageML/test.py
PyImageML-0.0.1.dist-info/LICENSE
PyImageML-0.0.1.dist-info/METADATA
PyImageML-0.0.1.dist-info/WHEEL
PyImageML-0.0.1.dist-info/top_level.txt
PyImageML-0.0.1.dist-info/RECORD
