Metadata-Version: 2.1
Name: PyImageML
Version: 0.0.1
Summary: This is a package that contains ML utils for dealing with images problems.
Home-page: https://github.com/FabioScielzoOrtiz/PyImageML_Package
Author: Fabio Scielzo Ortiz
Author-email: fabioscielzo98@gmail.com
Classifier: Programming Language :: Python :: 3
Classifier: License :: OSI Approved :: MIT License
Classifier: Operating System :: OS Independent
Requires-Python: >=3.7
License-File: LICENSE
Requires-Dist: pandas
Requires-Dist: numpy
